nucliadb_contributor_assets/3rdpartylicenses.txt
nucliadb_contributor_assets/945.2b87b788ee42edde.js
nucliadb_contributor_assets/__init__.py
nucliadb_contributor_assets/index.html
nucliadb_contributor_assets/main.379a56df094193ba.js
nucliadb_contributor_assets/polyfills.42c0348129e7e3a9.js
nucliadb_contributor_assets/runtime.a1a2c3996580edac.js
nucliadb_contributor_assets/source-code-pro-v14-latin-regular.c54f7f16da733fd8.woff
nucliadb_contributor_assets/source-code-pro-v14-latin-regular.e7bb30b550ed09e8.woff2
nucliadb_contributor_assets/styles.6a5e195432ef965c.css
nucliadb_contributor_assets/assets/glyphs-sprite.svg
nucliadb_contributor_assets/assets/connector-logos/algolia.svg
nucliadb_contributor_assets/assets/connector-logos/brightcove.svg
nucliadb_contributor_assets/assets/connector-logos/confluence.svg
nucliadb_contributor_assets/assets/connector-logos/dropbox.svg
nucliadb_contributor_assets/assets/connector-logos/folder.svg
nucliadb_contributor_assets/assets/connector-logos/gcs.svg
nucliadb_contributor_assets/assets/connector-logos/gdrive.svg
nucliadb_contributor_assets/assets/connector-logos/nucliacloud.svg
nucliadb_contributor_assets/assets/connector-logos/onedrive.svg
nucliadb_contributor_assets/assets/connector-logos/s3.svg
nucliadb_contributor_assets/assets/connector-logos/sharepoint.svg
nucliadb_contributor_assets/assets/connector-logos/sitemap.svg
nucliadb_contributor_assets/assets/deployment/app-config.json
nucliadb_contributor_assets/assets/deployment/app-config.json.bak
nucliadb_contributor_assets/assets/fonts/source-code-pro/source-code-pro-v14-latin-regular.woff
nucliadb_contributor_assets/assets/fonts/source-code-pro/source-code-pro-v14-latin-regular.woff2
nucliadb_contributor_assets/assets/fonts/videoagular/Videogular.json
nucliadb_contributor_assets/assets/fonts/videoagular/videogular.woff
nucliadb_contributor_assets/assets/i18n/common/ca.json
nucliadb_contributor_assets/assets/i18n/common/de.json
nucliadb_contributor_assets-1.0.0.post1125.dist-info/METADATA
nucliadb_contributor_assets-1.0.0.post1125.dist-info/WHEEL
nucliadb_contributor_assets-1.0.0.post1125.dist-info/top_level.txt
nucliadb_contributor_assets-1.0.0.post1125.dist-info/zip-safe
nucliadb_contributor_assets-1.0.0.post1125.dist-info/RECORD
