Metadata-Version: 2.1
Name: nucliadb-contributor-assets
Version: 1.0.0.post1125
Summary: Packaging of NulcliaDB Contributor JS app
Home-page: https://github.com/nucliadb/frontend
Author: Nuclia
Author-email: nucliadb@nuclia.com
License: UNKNOWN
Platform: UNKNOWN
